SpatialNode/__init__.py
SpatialNode/abstract_graph_model.py
SpatialNode/abstract_graph_model.pyi
SpatialNode/abstract_node_geometry.py
SpatialNode/abstract_node_geometry.pyi
SpatialNode/abstract_node_painter.py
SpatialNode/abstract_node_painter.pyi
SpatialNode/basic_graphics_scene.py
SpatialNode/basic_graphics_scene.pyi
SpatialNode/connection_graphics_object.py
SpatialNode/connection_graphics_object.pyi
SpatialNode/connection_id_utils.py
SpatialNode/connection_id_utils.pyi
SpatialNode/connection_painter.py
SpatialNode/connection_painter.pyi
SpatialNode/connection_state.py
SpatialNode/connection_state.pyi
SpatialNode/connection_style.py
SpatialNode/data_flow_graph_model.py
SpatialNode/data_flow_graph_model.pyi
SpatialNode/data_flow_graphics_scene.py
SpatialNode/data_flow_graphics_scene.pyi
SpatialNode/default_horizontal_node_geometry.py
SpatialNode/default_horizontal_node_geometry.pyi
SpatialNode/default_node_painter.py
SpatialNode/default_node_painter.pyi
SpatialNode/default_vertical_node_geometry.py
SpatialNode/default_vertical_node_geometry.pyi
SpatialNode/definitions.py
SpatialNode/graphics_view.py
SpatialNode/graphics_view.pyi
SpatialNode/graphics_view_style.py
SpatialNode/locate_node.py
SpatialNode/locate_node.pyi
SpatialNode/node_connection_interaction.py
SpatialNode/node_connection_interaction.pyi
SpatialNode/node_data.py
SpatialNode/node_data.pyi
SpatialNode/node_delegate_model.py
SpatialNode/node_delegate_model.pyi
SpatialNode/node_delegate_model_registry.py
SpatialNode/node_delegate_model_registry.pyi
SpatialNode/node_graphics_object.py
SpatialNode/node_graphics_object.pyi
SpatialNode/node_state.py
SpatialNode/node_state.pyi
SpatialNode/node_style.py
SpatialNode/serializable.py
SpatialNode/serializable.pyi
SpatialNode/style.py
SpatialNode/style.pyi
SpatialNode/style_collection.py
SpatialNode/undo_commands.py
SpatialNode/undo_commands.pyi
SpatialNode/resources/__init__.py
SpatialNode/resources/resource_rc.py
SpatialNode-0.0.1.post1.dist-info/LICENSE
SpatialNode-0.0.1.post1.dist-info/METADATA
SpatialNode-0.0.1.post1.dist-info/WHEEL
SpatialNode-0.0.1.post1.dist-info/top_level.txt
SpatialNode-0.0.1.post1.dist-info/RECORD
