Metadata-Version: 2.1
Name: SpatialNode
Version: 0.0.1.post1
Summary: a node graph framework
Author-email: yangfengzzz <yangfengzzz@hotmail.com>
Maintainer-email: yangfengzzz <yangfengzzz@hotmail.com>
License: The MIT License
Project-URL: Homepage, https://github.com/SpatialForce/SpatialNode
Project-URL: Bug Reports, https://github.com/SpatialForce/SpatialNode/issues
Project-URL: Source, https://github.com/SpatialForce/SpatialNode
Keywords: node editor,pyside6
Classifier: Development Status :: 3 - Alpha
Classifier: Intended Audience :: Developers
Classifier: Topic :: Software Development :: Libraries
Classifier: License :: OSI Approved :: MIT License
Requires-Python: >=3.12
License-File: LICENSE
Requires-Dist: PySide6
Requires-Dist: PySide6-Addons
Requires-Dist: PySide6-Essentials
Requires-Dist: shiboken6
